{
  "object_fqn": "main.bi_output.bi_output_finance_tables_bi_db_positions_opened_from_iban_parquet",
  "generated_at": "2026-05-19T15:01:24Z",
  "formula_count": 2,
  "formulas": [
    {
      "column": "PositionID",
      "formula": null,
      "expression_raw": null,
      "inputs": [],
      "transform_kind": "unknown",
      "evidence_lines": null,
      "reason": "no source code cached"
    },
    {
      "column": "DepositID",
      "formula": null,
      "expression_raw": null,
      "inputs": [],
      "transform_kind": "unknown",
      "evidence_lines": null,
      "reason": "no source code cached"
    }
  ],
  "source": null
}