{
  "schema": "EXW_Wallet",
  "object": "AmlValidations",
  "ddl_path": "c:\\Users\\guyman\\Documents\\github\\DataPlatform\\SynapseSQLPool1\\sql_dp_prod_we\\EXW_Wallet\\Tables\\EXW_Wallet.AmlValidations.sql",
  "lineage_path": null,
  "writer_sps_discovered": [],
  "candidates_found": 0,
  "resolved_synapse": 0,
  "resolved_production": 0,
  "resolved_sp": 0,
  "unresolved": 0,
  "bundle_path": "C:\\Users\\guyman\\Documents\\github\\Databricks_Knowledge\\audits\\regen-sample\\EXW_Wallet\\AmlValidations\\regen\\_upstream_bundle.md",
  "bundle_size_bytes": 1588,
  "resolutions": []
}