{
  "verdict": "PASS",
  "severity": null,
  "reason": "The downstream description matches the source meaning; the parenthetical implementation hint (ExchangeRate=1.0 implied) is an internal detail, not a different business quantity.",
  "proposed_fix": null,
  "raw_response": "{\"verdict\":\"PASS\",\"severity\":null,\"reason\":\"The downstream description matches the source meaning; the parenthetical implementation hint (ExchangeRate=1.0 implied) is an internal detail, not a different business quantity.\",\"proposed_fix\":null}\n",
  "cached": false
}