{
  "verdict": "PASS",
  "severity": null,
  "reason": "Both descriptions convey the same meaning; the downstream version merely omits the check-constraint name CHK_TB_Amount, which is an implementation detail not affecting business interpretation.",
  "proposed_fix": null,
  "raw_response": "{\"verdict\":\"PASS\",\"severity\":null,\"reason\":\"Both descriptions convey the same meaning; the downstream version merely omits the check-constraint name CHK_TB_Amount, which is an implementation detail not affecting business interpretation.\",\"proposed_fix\":null}\n",
  "cached": false
}