{
    "schema":  "BI_DB_dbo",
    "object":  "BI_DB_CIDFirstDates",
    "best_attempt":  2,
    "best_score":  7.3,
    "attempts":  [
                     {
                         "attempt":  1,
                         "writer_exit":  0,
                         "judge_exit":  0,
                         "verdict":  "FAIL",
                         "score":  7.0
                     },
                     {
                         "attempt":  2,
                         "writer_exit":  0,
                         "judge_exit":  0,
                         "verdict":  "FAIL",
                         "score":  7.30
                     }
                 ],
    "timestamp":  "2026-04-28T07:41:50.4622615+00:00"
}